turboroid/__init__.py
turboroid/app.py
turboroid/asgi.py
turboroid/config.py
turboroid/constants.py
turboroid/entry.py
turboroid/logger.py
turboroid/handlers/__init__.py
turboroid/handlers/inspection.py
turboroid/handlers/resolver.py
turboroid/http/__init__.py
turboroid/http/constants.py
turboroid/http/models.py
turboroid/http/request.py
turboroid/http/response.py
turboroid/lifespan/__init__.py
turboroid/lifespan/constants.py
turboroid/resources/__init__.py
turboroid/resources/banner.txt
turboroid/routing/__init__.py
turboroid/routing/decorators.py
turboroid/routing/registry.py
turboroid/routing/router.py
turboroid/utils/__init__.py
turboroid/utils/banner.py
turboroid/websockets/__init__.py
turboroid-0.1.0.dist-info/METADATA
turboroid-0.1.0.dist-info/WHEEL
turboroid-0.1.0.dist-info/licenses/LICENSE
turboroid-0.1.0.dist-info/RECORD
