Metadata-Version: 2.4
Name: turboroid
Version: 0.1.0
Summary: Turboroid is extremely fast, developer-friendly ASGI micro-framework for building high-performance applications.
Project-URL: Homepage, https://github.com/turborg/turboroid
Project-URL: Repository, https://github.com/turborg/turboroid
Project-URL: Bug Tracker, https://github.com/turborg/turboroid/issues
Author-email: stefanzc <stefanzc@turborg.com>
License: MIT
License-File: LICENSE
Keywords: api,asgi,async,fast,high-performance,micro-framework,minimalist,turboroid,web
Classifier: Development Status :: 3 - Alpha
Classifier: Environment :: Web Environment
Classifier: Framework :: AsyncIO
Classifier: Intended Audience :: Developers
Classifier: License :: OSI Approved :: MIT License
Classifier: Operating System :: OS Independent
Classifier: Programming Language :: Python
Classifier: Programming Language :: Python :: 3
Classifier: Programming Language :: Python :: 3 :: Only
Classifier: Programming Language :: Python :: 3.10
Classifier: Programming Language :: Python :: 3.11
Classifier: Programming Language :: Python :: 3.12
Classifier: Programming Language :: Python :: 3.13
Classifier: Programming Language :: Python :: 3.14
Classifier: Topic :: Internet :: WWW/HTTP :: HTTP Servers
Requires-Dist: anyio>=4.0
Requires-Dist: httptools<1.0.0,>=0.7
Requires-Dist: orjson<4.0.0,>=3.11
Requires-Dist: pydantic<3.0.0,>=2.0
Requires-Dist: turbolightdi<1.0.0,>=0.1.0
Provides-Extra: dev
Requires-Dist: granian[reload]; extra == 'dev'
Requires-Dist: httpx[http2]; extra == 'dev'
Requires-Dist: mypy; extra == 'dev'
Requires-Dist: pre-commit; extra == 'dev'
Requires-Dist: pytest; extra == 'dev'
Requires-Dist: pytest-asyncio; extra == 'dev'
Requires-Dist: ruff; extra == 'dev'
Requires-Dist: uvicorn; extra == 'dev'
